measurely/__init__.py
measurely/core.py
measurely_py-0.1.9.dist-info/LICENSE
measurely_py-0.1.9.dist-info/METADATA
measurely_py-0.1.9.dist-info/WHEEL
measurely_py-0.1.9.dist-info/top_level.txt
measurely_py-0.1.9.dist-info/RECORD
