Metadata-Version: 2.1
Name: measurely-py
Version: 0.1.9
Summary: A Python library for interacting with the Measurely API
Home-page: https://github.com/measurely-dev/measurely-py
Author: Measurely-dev, YasTheGoat, afz
Author-email: 
License: MIT
Classifier: Programming Language :: Python :: 3
Classifier: License :: OSI Approved :: MIT License
Classifier: Operating System :: OS Independent
Requires-Python: >=3.6
License-File: LICENSE
Requires-Dist: requests
